llm_multiprovider/__init__.py
llm_multiprovider/api.py
llm_multiprovider/models.py
llm_multiprovider/run.py
llm_multiprovider/providers/__init__.py
llm_multiprovider/providers/base.py
llm_multiprovider/providers/cerebras.py
llm_multiprovider/providers/groq.py
llm_multiprovider/providers/local.py
llm_multiprovider/providers/model_provider_factory.py
llm_multiprovider/providers/ollama.py
llm_multiprovider/providers/openai.py
llm_multiprovider/providers/openrouter.py
llm_multiprovider/providers/runpod.py
llm_multiprovider/providers/runpod_openai.py
llm_multiprovider/providers/testing_providers.py
llm_multiprovider/providers/testing_text_generation.py
llm_multiprovider/providers/together_ai.py
llm_multiprovider/utils/__init__.py
llm_multiprovider/utils/local_utils.py
llm_multiprovider/utils/metrics.py
llm_multiprovider/utils/request_utils.py
llm_multiprovider/utils/text_utils.py
llm_multiprovider/utils/tokenizer_mapper.py
llm_multiprovider-0.1.43.dist-info/licenses/LICENSE
llm_multiprovider-0.1.43.dist-info/METADATA
llm_multiprovider-0.1.43.dist-info/WHEEL
llm_multiprovider-0.1.43.dist-info/top_level.txt
llm_multiprovider-0.1.43.dist-info/RECORD
